{"body":"{\"data\":{\"Items\":[{\"event_id\":\"link_access\",\"server_timestamp\":1657291674286,\"client_id\":\"Windows_915\",\"client_timestamp\":\"1657291673807\"},{\"event_id\":\"link_access\",\"server_timestamp\":1657291626017,\"client_id\":\"Windows_173\",\"client_timestamp\":\"1657291625544\"},{\"event_id\":\"avatar_selected\",\"server_timestamp\":1657291704770,\"client_id\":\"Windows_137\",\"client_timestamp\":\"1657291704308\"},{\"event_id\":\"avatar_selected\",\"server_timestamp\":1657291691531,\"client_id\":\"Windows_396\",\"client_timestamp\":\"1657291691338\"},{\"event_id\":\"joined_room\",\"server_timestamp\":1657291696511,\"client_id\":\"Windows_915\",\"client_timestamp\":\"1657291696055\"},{\"event_id\":\"link_access\",\"server_timestamp\":1657291674400,\"client_id\":\"Windows_996\",\"client_timestamp\":\"1657291673947\"},{\"event_id\":\"joined_room\",\"server_timestamp\":1657291705701,\"client_id\":\"Windows_996\",\"client_timestamp\":\"1657291705241\"},{\"event_id\":\"link_access\",\"server_timestamp\":1657291678356,\"client_id\":\"Windows_396\",\"client_timestamp\":\"1657291678188\"},{\"event_id\":\"joined_room\",\"server_timestamp\":1657291701468,\"client_id\":\"Windows_732\",\"client_timestamp\":\"1657291700819\"},{\"event_id\":\"link_access\",\"server_timestamp\":1657291674436,\"client_id\":\"Windows_137\",\"client_timestamp\":\"1657291673969\"},{\"event_id\":\"avatar_selected\",\"server_timestamp\":1657291706943,\"client_id\":\"Windows_996\",\"client_timestamp\":\"1657291706475\"},{\"event_id\":\"link_access\",\"server_timestamp\":1657291674557,\"client_id\":\"Windows_732\",\"client_timestamp\":\"1657291674102\"},{\"event_id\":\"joined_room\",\"server_timestamp\":1657291704519,\"client_id\":\"Windows_137\",\"client_timestamp\":\"1657291704059\"},{\"event_id\":\"avatar_selected\",\"server_timestamp\":1657291701858,\"client_id\":\"Windows_732\",\"client_timestamp\":\"1657291701402\"},{\"event_id\":\"joined_room\",\"server_timestamp\":1657291691293,\"client_id\":\"Windows_396\",\"client_timestamp\":\"1657291691100\"}],\"Count\":15,\"ScannedCount\":2010}}"}