{"body":"{\"data\":{\"Items\":[{\"event_id\":\"joined_room\",\"server_timestamp\":1656676682562,\"client_id\":\"Linux_41\",\"client_timestamp\":\"1656676682237\"},{\"event_id\":\"link_access\",\"server_timestamp\":1656676610849,\"client_id\":\"Linux_139\",\"client_timestamp\":\"1656676610672\"},{\"event_id\":\"joined_room\",\"server_timestamp\":1656676681301,\"client_id\":\"Linux_253\",\"client_timestamp\":\"1656676681178\"},{\"event_id\":\"avatar_selected\",\"server_timestamp\":1656676684189,\"client_id\":\"Linux_139\",\"client_timestamp\":\"1656676684068\"},{\"event_id\":\"avatar_selected\",\"server_timestamp\":1656676682646,\"client_id\":\"Linux_253\",\"client_timestamp\":\"1656676682527\"},{\"event_id\":\"link_access\",\"server_timestamp\":1656676611203,\"client_id\":\"Windows_964\",\"client_timestamp\":\"1656676610026\"},{\"event_id\":\"avatar_selected\",\"server_timestamp\":1656676682332,\"client_id\":\"Linux_718\",\"client_timestamp\":\"1656676682213\"},{\"event_id\":\"avatar_selected\",\"server_timestamp\":1656676650189,\"client_id\":\"Windows_964\",\"client_timestamp\":\"1656676649708\"},{\"event_id\":\"link_access\",\"server_timestamp\":1656676610344,\"client_id\":\"Linux_41\",\"client_timestamp\":\"1656676610172\"},{\"event_id\":\"link_access\",\"server_timestamp\":1656676610760,\"client_id\":\"Linux_718\",\"client_timestamp\":\"1656676610641\"},{\"event_id\":\"avatar_selected\",\"server_timestamp\":1656676683442,\"client_id\":\"Linux_41\",\"client_timestamp\":\"1656676683252\"},{\"event_id\":\"joined_room\",\"server_timestamp\":1656676649928,\"client_id\":\"Windows_964\",\"client_timestamp\":\"1656676649461\"},{\"event_id\":\"link_access\",\"server_timestamp\":1656676508183,\"client_id\":\"Linux_421\",\"client_timestamp\":\"1656676507588\"},{\"event_id\":\"joined_room\",\"server_timestamp\":1656676681490,\"client_id\":\"Linux_718\",\"client_timestamp\":\"1656676681368\"},{\"event_id\":\"joined_room\",\"server_timestamp\":1656676683028,\"client_id\":\"Linux_139\",\"client_timestamp\":\"1656676682903\"},{\"event_id\":\"link_access\",\"server_timestamp\":1656676611169,\"client_id\":\"Linux_253\",\"client_timestamp\":\"1656676610286\"}],\"Count\":16,\"ScannedCount\":714}}"}